RandomDataGenerators/RandomDataFrameGenerator.py
RandomDataGenerators/RandomFunctions.py
RandomDataGenerators/__init__.py
RandomDataGenerators/resources/dfEnglishWords.csv
RandomDataGenerators/resources/dfPetNameCounts.csv
RandomDataGenerators-0.3.0.dist-info/LICENSE
RandomDataGenerators-0.3.0.dist-info/METADATA
RandomDataGenerators-0.3.0.dist-info/WHEEL
RandomDataGenerators-0.3.0.dist-info/top_level.txt
RandomDataGenerators-0.3.0.dist-info/RECORD
