Metadata-Version: 2.1
Name: RandomDataGenerators
Version: 0.3.0
Summary: Generator of random data frames.
Home-page: https://github.com/antononcube/Python-packages/tree/main/RandomDataGenerators
Author: Anton Antonov
Author-email: antononcube@posteo.net
Keywords: random,random data frame,random dataset,dataset,data,frame,random pet name,pet name,random word,word,random data generator,data generators,random job title,job title
Classifier: Intended Audience :: Science/Research
Classifier: Intended Audience :: Developers
Classifier: Programming Language :: Python :: 3
Classifier: License :: OSI Approved :: BSD License
Classifier: Intended Audience :: Science/Research
Classifier: Intended Audience :: Developers
Classifier: Operating System :: OS Independent
Requires-Python: >=3.7
License-File: LICENSE
Requires-Dist: numpy
Requires-Dist: pandas
Requires-Dist: StringGenerator
